schieber/__init__.py
schieber/card.py
schieber/dealer.py
schieber/deck.py
schieber/game.py
schieber/jass-server.py
schieber/stich.py
schieber/suit.py
schieber/team.py
schieber/tournament.py
schieber/trumpf.py
schieber/example/__init__.py
schieber/example/main.py
schieber/example/server_launcher.py
schieber/helpers/__init__.py
schieber/helpers/game_helper.py
schieber/player/__init__.py
schieber/player/base_player.py
schieber/player/cli_player.py
schieber/player/external_player.py
schieber/player/model_player.py
schieber/player/random_player.py
schieber/player/challenge_player/__init__.py
schieber/player/challenge_player/challenge_player.py
schieber/player/challenge_player/strategy/__init__.py
schieber/player/challenge_player/strategy/card_counter.py
schieber/player/challenge_player/strategy/jass_strategy.py
schieber/player/challenge_player/strategy/flags/__init__.py
schieber/player/challenge_player/strategy/flags/doesnt_habe_card_flag.py
schieber/player/challenge_player/strategy/flags/falied_to_serve_suit_flag.py
schieber/player/challenge_player/strategy/flags/previously_had_stich_flag.py
schieber/player/challenge_player/strategy/flags/suit_verworfen_flag.py
schieber/player/challenge_player/strategy/mode/__init__.py
schieber/player/challenge_player/strategy/mode/bottom_up_mode.py
schieber/player/challenge_player/strategy/mode/mode.py
schieber/player/challenge_player/strategy/mode/top_down_mode.py
schieber/player/challenge_player/strategy/mode/trumpf_color_mode.py
schieber/player/challenge_player/strategy/mode/uncolored_trumpf.py
schieber/player/greedy_player/__init__.py
schieber/player/greedy_player/greedy_player.py
schieber/player/greedy_player/trumpf_decision.py
schieber/player/server_player/__init__.py
schieber/player/server_player/server_player.py
schieber/player/server_player/helpers/__init__.py
schieber/player/server_player/helpers/messages.py
schieber/player/server_player/helpers/server_cards.py
schieber/player/server_player/helpers/web_socket_handler.py
schieber-0.1.10.dist-info/LICENSE
schieber-0.1.10.dist-info/METADATA
schieber-0.1.10.dist-info/WHEEL
schieber-0.1.10.dist-info/top_level.txt
schieber-0.1.10.dist-info/RECORD
