Metadata-Version: 2.1
Name: schieber
Version: 0.1.10
Summary: Schieber is a terminal application of the popular Swiss card game Schieber and provides an API to the game
Home-page: https://github.com/JoelNiklaus/schieber
Author: Joel Niklaus
Author-email: me@joelniklaus.ch
License: MIT License
